Ejercicio 6/ejercicio6.v


module FLIP (input clk, reset, D,
            output reg Y);
        always @ (posedge clk or posedge reset)begin
            if (reset) begin
                Y <= 1'b0;
            end
            else begin
                Y <= D;
            end
        end
endmodule


//Ejercicio 1

module ejercicio1(input A, B, clk, reset, output wire Y, output wire [1:0] S02, S12);
        wire S0, S1, S01, S11;
        assign S01 = (~S1 & ~S0 & A);
        assign S11 = (S0 & B) | (S1 & A & B);
        FLIP U1(clk, reset, S01, S0);
        FLIP U2(clk, reset, S11, S1);
        assign Y = (S1 & ~S0 & A & B);
        assign S02 = {S1 , S0};
        assign S12 = {S11, S01};

endmodule


//Ejercicio 3

module ejercicio3(input A, clk, reset, output wire Y1, Y2, Y3, output wire [2:0] S02, S12);
    wire S0, S1, S2, S00, S11, S22;

    assign S22 = (S2 & S1 & ~A) | (S2 & ~S0 & A) | (S2 & ~S1 & S0) | (~S2 & ~S1 & S0 & ~A) | (~S2 & S1 & S0 & A);
    assign S11 = (~S1 & ~S0 & ~A) | (S1 & S0 & ~A) | (S1 & ~S0 & A) | (~S1 & S0 & A);
    assign S00 = ~S0;

    FLIP U3(clk, reset, S22, S2);
    FLIP U4(clk, reset, S11, S1);
    FLIP U5(clk, reset, S00, S0);

    assign Y1 = S2;
    assign Y2 = (S2 & ~S1) | (~S2 & S1);
    assign Y3 = (S1 & ~S0) | (~S1 & S0);
    assign S02= {S2, S1, S0};
    assign S12= {S22, S11, S00};

endmodule

Ejercicio 6/testbench2_tb.v

module testbench();

    reg clk, reset0, A0, B0, reset1, A1;
    wire Y0, Y1, Y2, Y3;
    wire [1:0] Sf, Sp;
    wire [2:0] SF, SP;


    ejercicio1 U0(A0, B0, clk, reset0, Y0, Sp, Sf);
    ejercicio3 U1(A1, clk, reset1, Y1, Y2, Y3, SP, SF);

    initial begin
          $display("\n");
          $display("Ejercicio 1");
          $display("reset A B Sf Sp / Y");
          $monitor("%b %b %b %b %b/ %b", reset0, A0, B0, Sf, Sp,Y0);
            clk = 0; reset0 = 0; A0 = 0; B0 = 0;
            #1 reset0 = 1;
            #1 reset0 = 0; A0 = 1; B0 =1;

    end

    initial begin
          #16
          $display("\n");
          $display("Ejercicio 3");
          $display("reset A SF SP / Y1 Y2 Y3");
          $monitor("%b %b %b %b/ %b %b %b", reset1, A1, SF, SP, Y1, Y2, Y3);
            clk = 0; reset1 = 0; A1 = 0;
            #1 reset1 = 1;
            #8 A1 = 1; reset1 = 1;

    end

    always
      #5 clk = ~clk;


    initial
        #100 $finish;

    initial begin
      $dumpfile("testbench2_tb.vcd");
      $dumpvars(0, testbench);
    end
endmodule

Ejercicio 6/testbench2_tb.vcd
$date
	Sat Sep 05 23:05:47 2020
$end
$version
	Icarus Verilog
$end
$timescale
	1ps
$end
$scope module testbench $end
$var wire 1 ! Y3 $end
$var wire 1 " Y2 $end
$var wire 1 # Y1 $end
$var wire 1 $ Y0 $end
$var wire 2 % Sp [1:0] $end
$var wire 2 & Sf [1:0] $end
$var wire 3 ' SP [2:0] $end
$var wire 3 ( SF [2:0] $end
$var reg 1 ) A0 $end
$var reg 1 * A1 $end
$var reg 1 + B0 $end
$var reg 1 , clk $end
$var reg 1 - reset0 $end
$var reg 1 . reset1 $end
$scope module U0 $end
$var wire 1 ) A $end
$var wire 1 + B $end
$var wire 1 / S01 $end
$var wire 1 0 S11 $end
$var wire 1 $ Y $end
$var wire 1 , clk $end
$var wire 1 - reset $end
$var wire 2 1 S12 [1:0] $end
$var wire 1 2 S1 $end
$var wire 2 3 S02 [1:0] $end
$var wire 1 4 S0 $end
$scope module U1 $end
$var wire 1 / D $end
$var wire 1 , clk $end
$var wire 1 - reset $end
$var reg 1 4 Y $end
$upscope $end
$scope module U2 $end
$var wire 1 0 D $end
$var wire 1 , clk $end
$var wire 1 - reset $end
$var reg 1 2 Y $end
$upscope $end
$upscope $end
$scope module U1 $end
$var wire 1 * A $end
$var wire 1 5 S00 $end
$var wire 1 6 S11 $end
$var wire 1 7 S22 $end
$var wire 1 # Y1 $end
$var wire 1 " Y2 $end
$var wire 1 ! Y3 $end
$var wire 1 , clk $end
$var wire 1 . reset $end
$var wire 1 8 S2 $end
$var wire 3 9 S12 [2:0] $end
$var wire 1 : S1 $end
$var wire 3 ; S02 [2:0] $end
$var wire 1 < S0 $end
$scope module U3 $end
$var wire 1 7 D $end
$var wire 1 , clk $end
$var wire 1 . reset $end
$var reg 1 8 Y $end
$upscope $end
$scope module U4 $end
$var wire 1 6 D $end
$var wire 1 , clk $end
$var wire 1 . reset $end
$var reg 1 : Y $end
$upscope $end
$scope module U5 $end
$var wire 1 5 D $end
$var wire 1 , clk $end
$var wire 1 . reset $end
$var reg 1 < Y $end
$upscope $end
$upscope $end
$upscope $end
$enddefinitions $end
#0
$dumpvars
x<
bx ;
x:
bx 9
x8
x7
x6
x5
x4
bx 3
x2
b0 1
00
0/
x.
0-
0,
0+
x*
0)
bx (
bx '
b0 &
bx %
0$
x#
x"
x!
$end
#1
04
b0 %
b0 3
02
1-
#2
b1 &
b1 1
1/
1+
1)
0-
#5
0/
b10 &
b10 1
10
b1 %
b1 3
14
1,
#10
0,
#15
1$
04
b10 %
b10 3
12
1,
#16
0*
0.
0,
#17
07
16
0"
0!
b11 (
b11 9
15
0#
08
0:
b0 '
b0 ;
0<
1.
#20
1,
#25
b1 (
b1 9
06
0,
1*
